imagegengan/__init__.py
imagegengan/models.py
imagegengan/util.py
tests/__init__.py
imagegengan-1.0.2.dist-info/LICENSE.md
imagegengan-1.0.2.dist-info/METADATA
imagegengan-1.0.2.dist-info/WHEEL
imagegengan-1.0.2.dist-info/top_level.txt
imagegengan-1.0.2.dist-info/RECORD
