Metadata-Version: 2.1
Name: imagegengan
Version: 1.0.2
Summary: A plug-and-play GAN image generator.
Home-page: https://github.com/anthonykrivonos/imagegengan
Author: Anthony Krivonos
Author-email: info@anthonykrivonos.com
License: UNKNOWN
Platform: UNKNOWN
Classifier: Programming Language :: Python :: 3.7
Classifier: License :: OSI Approved :: MIT License
Classifier: Operating System :: OS Independent
Requires-Python: >=3.6
Requires-Dist: numpy
Requires-Dist: opencv-contrib-python
Requires-Dist: tensorflow
Requires-Dist: Keras
